CHANGELOG.md
cloudmask/__init__.py
cloudmask/cli.py
cloudmask/core.py
cloudmask/gui.py
cloudmask/models/.gitkeep
cloudmask-0.1.4.dist-info/entry_points.txt
cloudmask-0.1.4.dist-info/LICENSE
cloudmask-0.1.4.dist-info/WHEEL
cloudmask-0.1.4.dist-info/METADATA
cloudmask-0.1.4.dist-info/RECORD
