Metadata-Version: 2.1
Name: cloudmask
Version: 0.1.4
Summary: Cloud mask with Landsat 8
Home-page: https://github.com/XavierJiezou/CloudMask
License: MIT
Keywords: landsat8,cloud,mask
Author: XavierJiezou
Author-email: 878972272@qq.com
Requires-Python: >=3.7,<4.0
Classifier: License :: OSI Approved :: MIT License
Classifier: Programming Language :: Python :: 3
Classifier: Programming Language :: Python :: 3.10
Classifier: Programming Language :: Python :: 3.7
Classifier: Programming Language :: Python :: 3.8
Classifier: Programming Language :: Python :: 3.9
Classifier: Topic :: Software Development :: Libraries :: Python Modules
Requires-Dist: fire (>=0.4.0,<0.5.0)
Requires-Dist: rich (>=12.3.0,<13.0.0)
Project-URL: Documentation, https://github.com/XavierJiezou/CloudMask
Project-URL: Repository, https://github.com/XavierJiezou/CloudMask
